klu/__init__.py
klu/action/__init__.py
klu/action/client.py
klu/action/constants.py
klu/action/errors.py
klu/action/models.py
klu/api/__init__.py
klu/api/client.py
klu/api/config.py
klu/api/constants.py
klu/api/sse_client.py
klu/app/__init__.py
klu/app/client.py
klu/app/constants.py
klu/app/errors.py
klu/app/models.py
klu/client/__init__.py
klu/client/klu.py
klu/common/__init__.py
klu/common/client.py
klu/common/errors.py
klu/common/models.py
klu/context/__init__.py
klu/context/client.py
klu/context/constants.py
klu/context/errors.py
klu/context/models.py
klu/data/__init__.py
klu/data/client.py
klu/data/constants.py
klu/data/errors.py
klu/data/models.py
klu/dataset/__init__.py
klu/dataset/client.py
klu/dataset/constants.py
klu/dataset/errors.py
klu/dataset/models.py
klu/evals/__init__.py
klu/evals/client.py
klu/evals/constants.py
klu/evals/errors.py
klu/evals/models.py
klu/experiment/__init__.py
klu/experiment/client.py
klu/experiment/constants.py
klu/experiment/errors.py
klu/experiment/models.py
klu/feedback/__init__.py
klu/feedback/client.py
klu/feedback/constants.py
klu/feedback/errors.py
klu/feedback/models.py
klu/finetune/__init__.py
klu/finetune/client.py
klu/finetune/constants.py
klu/finetune/errors.py
klu/finetune/models.py
klu/klu.py
klu/model/__init__.py
klu/model/client.py
klu/model/constants.py
klu/model/errors.py
klu/model/models.py
klu/session/__init__.py
klu/session/client.py
klu/session/constants.py
klu/session/models.py
klu/skill/__init__.py
klu/skill/client.py
klu/skill/constants.py
klu/skill/models.py
klu/utils/dict_helpers.py
klu/utils/file_upload.py
klu/utils/paginator.py
klu/workflows/__init__.py
klu/workflows/client.py
klu/workflows/constants.py
klu/workflows/models.py
klu/workspace/__init__.py
klu/workspace/client.py
klu/workspace/constants.py
klu/workspace/errors.py
klu/workspace/models.py
klu-0.1.80.dist-info/LICENSE
klu-0.1.80.dist-info/METADATA
klu-0.1.80.dist-info/WHEEL
klu-0.1.80.dist-info/RECORD
